ros_std_srvs-5.5.1.data/data/include/std_srvs/std_srvs/msg/rosidl_generator_c__visibility_control.h
ros_std_srvs-5.5.1.data/data/include/std_srvs/std_srvs/msg/rosidl_generator_cpp__visibility_control.hpp
ros_std_srvs-5.5.1.data/data/include/std_srvs/std_srvs/msg/rosidl_typesupport_fastrtps_c__visibility_control.h
ros_std_srvs-5.5.1.data/data/include/std_srvs/std_srvs/msg/rosidl_typesupport_fastrtps_cpp__visibility_control.h
ros_std_srvs-5.5.1.data/data/include/std_srvs/std_srvs/msg/rosidl_typesupport_introspection_c__visibility_control.h
ros_std_srvs-5.5.1.data/data/include/std_srvs/std_srvs/srv/empty.h
ros_std_srvs-5.5.1.data/data/include/std_srvs/std_srvs/srv/empty.hpp
ros_std_srvs-5.5.1.data/data/include/std_srvs/std_srvs/srv/set_bool.h
ros_std_srvs-5.5.1.data/data/include/std_srvs/std_srvs/srv/set_bool.hpp
ros_std_srvs-5.5.1.data/data/include/std_srvs/std_srvs/srv/trigger.h
ros_std_srvs-5.5.1.data/data/include/std_srvs/std_srvs/srv/trigger.hpp
ros_std_srvs-5.5.1.data/data/include/std_srvs/std_srvs/srv/detail/empty__builder.hpp
ros_std_srvs-5.5.1.data/data/include/std_srvs/std_srvs/srv/detail/empty__description.c
ros_std_srvs-5.5.1.data/data/include/std_srvs/std_srvs/srv/detail/empty__functions.c
ros_std_srvs-5.5.1.data/data/include/std_srvs/std_srvs/srv/detail/empty__functions.h
ros_std_srvs-5.5.1.data/data/include/std_srvs/std_srvs/srv/detail/empty__rosidl_typesupport_fastrtps_c.h
ros_std_srvs-5.5.1.data/data/include/std_srvs/std_srvs/srv/detail/empty__rosidl_typesupport_fastrtps_cpp.hpp
ros_std_srvs-5.5.1.data/data/include/std_srvs/std_srvs/srv/detail/empty__rosidl_typesupport_introspection_c.h
ros_std_srvs-5.5.1.data/data/include/std_srvs/std_srvs/srv/detail/empty__rosidl_typesupport_introspection_cpp.hpp
ros_std_srvs-5.5.1.data/data/include/std_srvs/std_srvs/srv/detail/empty__struct.h
ros_std_srvs-5.5.1.data/data/include/std_srvs/std_srvs/srv/detail/empty__struct.hpp
ros_std_srvs-5.5.1.data/data/lib/python3.10/site-packages/std_srvs-5.5.1-py3.10.egg-info/PKG-INFO
ros_std_srvs-5.5.1.data/data/lib/python3.10/site-packages/std_srvs-5.5.1-py3.10.egg-info/SOURCES.txt
ros_std_srvs-5.5.1.data/data/lib/python3.10/site-packages/std_srvs-5.5.1-py3.10.egg-info/dependency_links.txt
ros_std_srvs-5.5.1.data/data/lib/python3.10/site-packages/std_srvs-5.5.1-py3.10.egg-info/top_level.txt
ros_std_srvs-5.5.1.dist-info/METADATA
ros_std_srvs-5.5.1.dist-info/WHEEL
ros_std_srvs-5.5.1.dist-info/top_level.txt
ros_std_srvs-5.5.1.dist-info/RECORD
ros_std_srvs-5.5.1.dist-info/licenses/LICENSE
