Metadata-Version: 2.4
Name: ros-std-srvs
Version: 5.5.1
Summary: This ROS package, std_srvs, offers standard and simple service definitions like Empty, SetBool, and Trigger for basic ROS interactions.
License-File: LICENSE
Requires-Dist: ros-rosidl-default-runtime~=1.7.1
Dynamic: description
Dynamic: description-content-type
Dynamic: license-file
Dynamic: requires-dist
Dynamic: summary
